topsis/__init__.py
topsis/__main__.py
Topsis_Jashan_102003206-1.0.0.dist-info/LICENSE
Topsis_Jashan_102003206-1.0.0.dist-info/METADATA
Topsis_Jashan_102003206-1.0.0.dist-info/WHEEL
Topsis_Jashan_102003206-1.0.0.dist-info/entry_points.txt
Topsis_Jashan_102003206-1.0.0.dist-info/top_level.txt
Topsis_Jashan_102003206-1.0.0.dist-info/RECORD
